drf_nested_resources/__init__.py
drf_nested_resources/_forged_request.py
drf_nested_resources/fields.py
drf_nested_resources/lookup_helpers.py
drf_nested_resources/routers.py
drf_nested_resources-2.0.0.dist-info/LICENSE.txt
drf_nested_resources-2.0.0.dist-info/METADATA
drf_nested_resources-2.0.0.dist-info/WHEEL
drf_nested_resources-2.0.0.dist-info/top_level.txt
drf_nested_resources-2.0.0.dist-info/RECORD
