Metadata-Version: 2.1
Name: drf-nested-resources
Version: 2.0.0
Summary: Support for nested routes in the Django REST Framework
Home-page: https://pypi.python.org/pypi/drf-nested-resources
Author: 2degrees Limited
Author-email: foss@2degreesnetwork.com
License: BSD (http://dev.2degreesnetwork.com/p/2degrees-license.html)
Platform: UNKNOWN
Classifier: Development Status :: 5 - Production/Stable
Classifier: Intended Audience :: Developers
Classifier: License :: OSI Approved :: BSD License
Classifier: Natural Language :: English
Classifier: Operating System :: OS Independent
Classifier: Programming Language :: Python :: 3
Classifier: Topic :: Software Development :: Libraries
Requires-Dist: djangorestframework (>=3.9.2)
Requires-Dist: pyrecord (>=1.0rc2)
